pyschematron/__init__.py
pyschematron/__version__.py
pyschematron/api.py
pyschematron/cli.py
pyschematron/utils.py
pyschematron/direct_mode/__init__.py
pyschematron/direct_mode/api.py
pyschematron/direct_mode/lib/__init__.py
pyschematron/direct_mode/lib/ast.py
pyschematron/direct_mode/schematron/__init__.py
pyschematron/direct_mode/schematron/ast.py
pyschematron/direct_mode/schematron/ast_visitors.py
pyschematron/direct_mode/schematron/ast_yaml.py
pyschematron/direct_mode/schematron/utils.py
pyschematron/direct_mode/schematron/parsers/__init__.py
pyschematron/direct_mode/schematron/parsers/xml/__init__.py
pyschematron/direct_mode/schematron/parsers/xml/builders.py
pyschematron/direct_mode/schematron/parsers/xml/parser.py
pyschematron/direct_mode/schematron/parsers/xml/utils.py
pyschematron/direct_mode/svrl/__init__.py
pyschematron/direct_mode/svrl/ast.py
pyschematron/direct_mode/svrl/svrl_visitors.py
pyschematron/direct_mode/svrl/xml_writer.py
pyschematron/direct_mode/xml_validation/__init__.py
pyschematron/direct_mode/xml_validation/validators.py
pyschematron/direct_mode/xml_validation/queries/__init__.py
pyschematron/direct_mode/xml_validation/queries/base.py
pyschematron/direct_mode/xml_validation/queries/exceptions.py
pyschematron/direct_mode/xml_validation/queries/factories.py
pyschematron/direct_mode/xml_validation/queries/xpath.py
pyschematron/direct_mode/xml_validation/results/__init__.py
pyschematron/direct_mode/xml_validation/results/svrl_builder.py
pyschematron/direct_mode/xml_validation/results/validation_results.py
pyschematron/direct_mode/xml_validation/results/xml_nodes.py
pyschematron-1.1.13.dist-info/entry_points.txt
pyschematron-1.1.13.dist-info/LICENSE
pyschematron-1.1.13.dist-info/WHEEL
pyschematron-1.1.13.dist-info/METADATA
pyschematron-1.1.13.dist-info/RECORD
