Metadata-Version: 2.1
Name: pyschematron
Version: 1.1.13
Summary: Schematron validation in Python.
Keywords: Schematron,XML validation
Author-email: Robbert Harms <robbert@xkls.nl>
Requires-Python: >=3.12
Classifier: Development Status :: 5 - Production/Stable
Classifier: Environment :: Console
Classifier: Intended Audience :: Developers
Classifier: Natural Language :: English
Classifier: License :: OSI Approved :: GNU General Public License v3 or later (GPLv3+)
Classifier: Programming Language :: Python :: 3.12
Requires-Dist: xmlschema~=4.1.0
Requires-Dist: elementpath~=5.0.4
Requires-Dist: typer>=0.19.2
Requires-Dist: appdirs~=1.4.4
Requires-Dist: lxml~=6.0.0
Requires-Dist: Jinja2~=3.1.6
Requires-Dist: ruyaml~=0.91.0
Requires-Dist: frozendict~=2.4.6
Requires-Dist: Sphinx~=8.2.0 ; extra == "doc"
Requires-Dist: git-cliff~=2.8.0 ; extra == "doc"
Requires-Dist: pytest~=8.3.4 ; extra == "test"
Requires-Dist: pytest-check~=2.5.0 ; extra == "test"
Requires-Dist: pytest-cov~=6.0.0 ; extra == "test"
Requires-Dist: pytest-html~=4.1.1 ; extra == "test"
Requires-Dist: tox~=4.24.1 ; extra == "test"
Project-URL: Homepage, https://github.com/robbert-harms/pyschematron/
Provides-Extra: doc
Provides-Extra: test
